showdialog/__init__.py
showdialog-1.0.3.dist-info/LICENSE
showdialog-1.0.3.dist-info/METADATA
showdialog-1.0.3.dist-info/WHEEL
showdialog-1.0.3.dist-info/top_level.txt
showdialog-1.0.3.dist-info/RECORD
