Metadata-Version: 2.1
Name: showdialog
Version: 1.0.3
Summary: Simple module for showing GTK dialog
Author: Chechkenev Andrey (@DarkCat09)
Author-email: aacd0709@mail.ru
Classifier: Development Status :: 5 - Production/Stable
Classifier: Programming Language :: Python :: 3
Classifier: License :: OSI Approved :: MIT License
Classifier: Operating System :: OS Independent
Classifier: Environment :: X11 Applications :: GTK
Requires-Python: >=3.6
License-File: LICENSE
Requires-Dist: PyGObject (>=3.42.2)
